json_config_expander/__init__.py
json_config_expander/cartesian_product_config_expander.py
json_config_expander/config_expander.py
json_config_expander/find_and_replace_config_expander.py
json_config_expander-0.6.dist-info/LICENSE
json_config_expander-0.6.dist-info/METADATA
json_config_expander-0.6.dist-info/WHEEL
json_config_expander-0.6.dist-info/top_level.txt
json_config_expander-0.6.dist-info/RECORD
