Metadata-Version: 2.1
Name: json-config-expander
Version: 0.6
Summary: Expand multi optional configuration to multiple configurations.
Home-page: https://github.com/DiagnosticRobotics/json-config-expander
Author: Diagnostic Robotics
Author-email: admin@diagnosticrobotics.com
License: MIT
Keywords: multiple json config
Platform: UNKNOWN
Classifier: Development Status :: 3 - Alpha
